fritznagios
